chromo_map/__init__.py
chromo_map/color.py
chromo_map/data/__init__.py
chromo_map/data/mpl_cat_names.json
tests/__init__.py
tests/test_color.py
chromo_map-0.1.15.dist-info/LICENSE
chromo_map-0.1.15.dist-info/METADATA
chromo_map-0.1.15.dist-info/WHEEL
chromo_map-0.1.15.dist-info/top_level.txt
chromo_map-0.1.15.dist-info/RECORD
