Metadata-Version: 2.1
Name: chromo_map
Version: 0.1.15
Summary: A Python package for manipulating color maps.
Home-page: https://github.com/pirsquared/chromo-map
Author: Sean Smith
Author-email: Sean Smith <pirsquared.pirr@gmail.com>
License: MIT
Project-URL: Homepage, https://github.com/pirsquared/Str2D
Classifier: Programming Language :: Python :: 3
Classifier: License :: OSI Approved :: MIT License
Classifier: Operating System :: OS Independent
Requires-Python: >=3.8
License-File: LICENSE
Requires-Dist: numpy
Requires-Dist: plotly
Requires-Dist: matplotlib >=3.7.5
Requires-Dist: pirrtools >=0.2.10
Requires-Dist: palettable
Requires-Dist: svgwrite
Requires-Dist: ipython
Requires-Dist: importlib-resources
Requires-Dist: bs4
Provides-Extra: dev
Requires-Dist: pytest ; extra == 'dev'
Requires-Dist: pytest-cov ; extra == 'dev'
Requires-Dist: build ; extra == 'dev'
Requires-Dist: twine ; extra == 'dev'
Requires-Dist: black ; extra == 'dev'
Requires-Dist: pre-commit ; extra == 'dev'
Requires-Dist: pylint ; extra == 'dev'
Requires-Dist: ipykernel ; extra == 'dev'
Requires-Dist: sphinx ; extra == 'dev'
Requires-Dist: sphinx-rtd-theme ; extra == 'dev'
Requires-Dist: sphinx-copybutton ; extra == 'dev'
Requires-Dist: sphinx-autobuild ; extra == 'dev'
Requires-Dist: sphinx-autodoc-typehints ; extra == 'dev'
Requires-Dist: ipython ; extra == 'dev'
Requires-Dist: coveralls ; extra == 'dev'
